{
  "users": [
    {
      "id": "d159",
      "fullName": "riri",
      "email": "fjru",
      "phone": "ruru",
      "password": ""
    }
  ],
  "login": [],
  "bills": [
    {
      "id": "1",
      "name": "Electric",
      "amout": 895.7,
      "dueDate": "July 12 2023",
      "status": "pending",
      "user_id": 1
    }
  ],
  "transactions": [
    {
      "id": "1",
      "name": "Electric",
      "amout": 895.7,
      "dueDate": "July 12 2023",
      "status": "pending",
      "user_id": 1
    }
  ]
}